memochain/__init__.py
memochain/client.py
memochain/groq_client.py
memochain/list_sessions.py
memochain/memory_store.py
memochain/session.py
memochain/utils.py
memochain-0.1.1.dist-info/METADATA
memochain-0.1.1.dist-info/WHEEL
memochain-0.1.1.dist-info/entry_points.txt
memochain-0.1.1.dist-info/top_level.txt
memochain-0.1.1.dist-info/RECORD
