Metadata-Version: 2.4
Name: memochain
Version: 0.1.1
Summary: A lightweight library to add memory to stateless LLM APIs
Author-email: Yash Thapliyal <yash.thapliyal@berkeley.edu>
Requires-Python: >=3.8
Requires-Dist: requests
